pyxirr-0.10.8.dist-info/METADATA
pyxirr-0.10.8.dist-info/WHEEL
pyxirr-0.10.8.dist-info/licenses/LICENSE
pyxirr.libs/libgcc_s-98a1ef30.so.1
pyxirr/__init__.py
pyxirr/_pyxirr.pyi
pyxirr/py.typed
pyxirr/pe.pyi
pyxirr/_pyxirr.cpython-310-x86_64-linux-gnu.so
pyxirr-0.10.8.dist-info/RECORD
