Metadata-Version: 2.3
Name: pyxirr
Version: 0.10.8
Classifier: Development Status :: 4 - Beta
Classifier: Topic :: Office/Business :: Financial
Classifier: Programming Language :: Rust
Classifier: Programming Language :: Python :: Implementation :: CPython
Classifier: Programming Language :: Python :: 3.7
Classifier: Programming Language :: Python :: 3.8
Classifier: Programming Language :: Python :: 3.9
Classifier: Programming Language :: Python :: 3.10
Classifier: Programming Language :: Python :: 3.11
Classifier: Programming Language :: Python :: 3.12
Classifier: Programming Language :: Python :: 3.13
Classifier: Programming Language :: Python :: 3.14
Classifier: License :: OSI Approved :: The Unlicense (Unlicense)
License-File: LICENSE
Summary: Rust-powered collection of financial functions for Python.
Keywords: python,fast,financial,xirr,cashflow,day count convention,PME
Home-Page: https://github.com/Anexen/pyxirr
Author: Anexen
License: Unlicense
Requires-Python: >=3.7
